pyrematch.libs/libgcc_s-a04fdf82.so.1
pyrematch.libs/libstdc++-a9383cce.so.6.0.28
pyrematch-1.1.4.dist-info/top_level.txt
pyrematch-1.1.4.dist-info/RECORD
pyrematch-1.1.4.dist-info/LICENSE
pyrematch-1.1.4.dist-info/METADATA
pyrematch-1.1.4.dist-info/WHEEL
pyrematch/__init__.py
pyrematch/_pyrematch.cpython-312-x86_64-linux-musl.so
pyrematch/pyrematch.py
